molecule_openstack/__init__.py
molecule_openstack/driver.py
molecule_openstack/cookiecutter/cookiecutter.json
molecule_openstack/cookiecutter/{{cookiecutter.molecule_directory}}/{{cookiecutter.scenario_name}}/INSTALL.rst
molecule_openstack/cookiecutter/{{cookiecutter.molecule_directory}}/{{cookiecutter.scenario_name}}/converge.yml
molecule_openstack/cookiecutter/{{cookiecutter.molecule_directory}}/{{cookiecutter.scenario_name}}/create.yml
molecule_openstack/cookiecutter/{{cookiecutter.molecule_directory}}/{{cookiecutter.scenario_name}}/destroy.yml
molecule_openstack/cookiecutter/{{cookiecutter.molecule_directory}}/{{cookiecutter.scenario_name}}/molecule.yml
molecule_openstack/cookiecutter/{{cookiecutter.molecule_directory}}/{{cookiecutter.scenario_name}}/prepare.yml
molecule_openstack/test/__init__.py
molecule_openstack/test/test_driver.py
molecule_openstack/test/functional/__init__.py
molecule_openstack/test/functional/test_func.py
molecule_openstack-0.3.dist-info/LICENSE
molecule_openstack-0.3.dist-info/METADATA
molecule_openstack-0.3.dist-info/WHEEL
molecule_openstack-0.3.dist-info/entry_points.txt
molecule_openstack-0.3.dist-info/top_level.txt
molecule_openstack-0.3.dist-info/RECORD
