Metadata-Version: 2.1
Name: molecule-openstack
Version: 0.3
Summary: Molecule OpenStack Plugin :: run molecule tests on openstack
Home-page: https://github.com/ansible-community/molecule-openstack
Author: Ansible by Red Hat
Author-email: info@ansible.com
Maintainer: Ansible by Red Hat
Maintainer-email: info@ansible.com
License: MIT
Project-URL: Bug Tracker, https://github.com/ansible-community/molecule-openstack/issues
Project-URL: Release Management, https://github.com/ansible-community/molecule-openstack/projects
Project-URL: CI, https://github.com/ansible-community/molecule-openstack/actions
Project-URL: Discussions, https://github.com/ansible-community/molecule/discussions
Project-URL: Source Code, https://github.com/ansible-community/molecule-openstack
Keywords: ansible,roles,testing,molecule,plugin,openstack
Platform: UNKNOWN
Classifier: Development Status :: 4 - Beta
Classifier: Environment :: Console
Classifier: Intended Audience :: Developers
Classifier: Intended Audience :: Information Technology
Classifier: Intended Audience :: System Administrators
Classifier: License :: OSI Approved :: MIT License
Classifier: Natural Language :: English
Classifier: Operating System :: OS Independent
Classifier: Programming Language :: Python :: 3
Classifier: Programming Language :: Python :: 3.6
Classifier: Programming Language :: Python :: 3.7
Classifier: Programming Language :: Python :: 3.8
Classifier: Programming Language :: Python :: 3.9
Classifier: Topic :: System :: Systems Administration
Classifier: Topic :: Utilities
Requires-Python: >=3.6
Requires-Dist: molecule (>=3.2.0)
Requires-Dist: pyyaml (<6,>=5.1)
Provides-Extra: test
Requires-Dist: molecule[test] ; extra == 'test'
